mmcb_rs232/__init__.py
mmcb_rs232/common.py
mmcb_rs232/detect.py
mmcb_rs232/dmm.py
mmcb_rs232/dmm_interface.py
mmcb_rs232/iv.py
mmcb_rs232/lexicon.py
mmcb_rs232/psuset.py
mmcb_rs232/psustat.py
mmcb_rs232/psuwatch.py
mmcb_rs232/sequence.py
mmcb_rs232/ult80.py
mmcb_rs232_avt-1.0.20.dist-info/METADATA
mmcb_rs232_avt-1.0.20.dist-info/WHEEL
mmcb_rs232_avt-1.0.20.dist-info/entry_points.txt
mmcb_rs232_avt-1.0.20.dist-info/top_level.txt
mmcb_rs232_avt-1.0.20.dist-info/RECORD
