Metadata-Version: 2.4
Name: mmcb_rs232-avt
Version: 1.0.20
Summary: ATLAS ITK Pixels Multi-Module Cycling Box environmental monitoring/control (RS232)
Home-page: https://gitlab.ph.liv.ac.uk/avt/atlas-itk-pmmcb-rs232
Author: Alan Taylor
Author-email: avt@hep.ph.liv.ac.uk
Maintainer: Alan Taylor
Maintainer-email: avt@hep.ph.liv.ac.uk
Classifier: Development Status :: 4 - Beta
Classifier: Intended Audience :: Developers
Classifier: Intended Audience :: Science/Research
Classifier: Topic :: Scientific/Engineering :: Physics
Classifier: Environment :: Console
Classifier: Environment :: X11 Applications
Classifier: Programming Language :: Python :: 3
Classifier: Programming Language :: Python :: 3 :: Only
Classifier: Programming Language :: Python :: 3.6
Classifier: Programming Language :: Python :: 3.7
Classifier: Programming Language :: Python :: 3.8
Classifier: Programming Language :: Python :: 3.9
Classifier: Programming Language :: Python :: 3.10
Classifier: Programming Language :: Python :: 3.11
Classifier: Programming Language :: Python :: 3.12
Classifier: Programming Language :: Python :: 3.13
Classifier: Operating System :: POSIX :: Linux
Classifier: Natural Language :: English
Classifier: License :: OSI Approved :: European Union Public Licence 1.2 (EUPL 1.2)
Requires-Python: >=3.6
Requires-Dist: numpy
Requires-Dist: pandas
Requires-Dist: matplotlib
Requires-Dist: zmq
Requires-Dist: pyserial==3.4.*
Requires-Dist: tables
Requires-Dist: yoctopuce
Dynamic: author
Dynamic: author-email
Dynamic: classifier
Dynamic: description
Dynamic: description-content-type
Dynamic: home-page
Dynamic: maintainer
Dynamic: maintainer-email
Dynamic: requires-dist
Dynamic: requires-python
Dynamic: summary
